[
  {
    "id": "a75efc2e",
    "userName": "Шашин ",
    "results": [
      {
        "category": "Логика",
        "game": {
          "gameName": "Что лишнее",
          "lvl": {
            "lvlNumber": 1,
            "date": "Год - 2024, Число - 28, Час - 1; Минута - 13",
            "result": "Плохо"
          }
        }
      },
      {
        "category": "Логика",
        "game": {
          "gameName": "Что лишнее",
          "lvl": {
            "lvlNumber": 2,
            "date": "Год - 2024, Число - 28, Час - 1; Минута - 13",
            "result": "Плохо"
          }
        }
      },
      {
        "category": "Логика",
        "game": {
          "gameName": "Что лишнее",
          "lvl": {
            "lvlNumber": 3,
            "date": "Год - 2024, Число - 28, Час - 1; Минута - 13",
            "result": "Хорошо"
          }
        }
      },
      {
        "category": "Шахматы",
        "game": {
          "gameName": "Кто так ходит",
          "lvl": {
            "lvlNumber": 1,
            "date": "Год - 2024, Число - 28, Час - 1; Минута - 16",
            "result": "Хорошо"
          }
        }
      },
      {
        "category": "Шахматы",
        "game": {
          "gameName": "Кто так ходит",
          "lvl": {
            "lvlNumber": 2,
            "date": "Год - 2024, Число - 28, Час - 1; Минута - 16",
            "result": "Плохо"
          }
        }
      },
      {
        "category": "Шахматы",
        "game": {
          "gameName": "Кто так ходит",
          "lvl": {
            "lvlNumber": 3,
            "date": "Год - 2024, Число - 28, Час - 1; Минута - 16",
            "result": "Хорошо"
          }
        }
      }
    ]
  }
]